AUTHORS.txt
LICENSE
MANIFEST.in
README.md
requirements.txt
setup.cfg
setup.py
pip-requirements/base.txt
pip-requirements/dev.txt
src/xamcheck_utils/__init__.py
src/xamcheck_utils/collections.py
src/xamcheck_utils/conversions.py
src/xamcheck_utils/crypto.py
src/xamcheck_utils/excel.py
src/xamcheck_utils/exceptions.py
src/xamcheck_utils/func.py
src/xamcheck_utils/html.py
src/xamcheck_utils/importlib.py
src/xamcheck_utils/text.py
src/xamcheck_utils.egg-info/PKG-INFO
src/xamcheck_utils.egg-info/SOURCES.txt
src/xamcheck_utils.egg-info/dependency_links.txt
src/xamcheck_utils.egg-info/namespace_packages.txt
src/xamcheck_utils.egg-info/not-zip-safe
src/xamcheck_utils.egg-info/pbr.json
src/xamcheck_utils.egg-info/requires.txt
src/xamcheck_utils.egg-info/top_level.txt
src/xamcheck_utils/tests/__init__.py
src/xamcheck_utils/tests/base.py
src/xamcheck_utils/tests/test_collections.py
src/xamcheck_utils/tests/test_conversions.py
src/xamcheck_utils/tests/test_crypto.py
src/xamcheck_utils/tests/test_excel.py
src/xamcheck_utils/tests/test_func.py
src/xamcheck_utils/tests/test_html.py
src/xamcheck_utils/tests/test_importlib.py
src/xamcheck_utils/tests/test_text.py