Metadata-Version: 1.1
Name: xamcheck-utils
Version: 0.0.13
Summary: Utility functions used in python projects of Xamcheck.
Home-page: https://github.com/psjinx/xamcheck-utils
Author: Pankaj Singh
Author-email: pankaj@xamcheck.com
License: BSD
Keywords: xamcheck utility
Platform: UNKNOWN
Classifier: Development Status :: 3 - Alpha
Classifier: Topic :: Utilities
Classifier: License :: OSI Approved :: BSD License
